docs/__init__.py
docs/urls.py
docs/views.py
docs/tests/__init__.py
docs/tests/runtests.py
docs/tests/test_views.py
docs/tests/urls.py
docs/tests/test_docs/index.html
docs/tests/test_docs/sub_dir/index.html
django4_docs-0.4.0.dist-info/AUTHORS
django4_docs-0.4.0.dist-info/LICENSE
django4_docs-0.4.0.dist-info/METADATA
django4_docs-0.4.0.dist-info/WHEEL
django4_docs-0.4.0.dist-info/top_level.txt
django4_docs-0.4.0.dist-info/RECORD
