Metadata-Version: 2.1
Name: django4-docs
Version: 0.4.0
Summary: Allows to serve Sphinx generated docs from django.
Home-page: https://github.com/jonasbohmann/django4-docs
Author: Evgeny Demchenko
Author-email: little_pea@list.ru
License: BSD
Classifier: Topic :: Internet :: WWW/HTTP :: Dynamic Content
Classifier: Intended Audience :: Developers
Classifier: Programming Language :: Python
Classifier: Programming Language :: Python :: 3
Classifier: Programming Language :: Python :: 2
Classifier: Framework :: Django
Classifier: Development Status :: 4 - Beta
Classifier: Operating System :: OS Independent
License-File: LICENSE
License-File: AUTHORS
Requires-Dist: Django (>=1.11)
